Workbook

Sheet Start Here
B2: Ultimate Trip Planner
B3: by The Geek Next Door Co.
B5: How to use this template
B7: 1. Fill in the Trip Overview tab: where you're going, dates, travellers and total budget. The countdown and trip length work themselves out.
B8: 2. Plan each day on the Itinerary tab — times, activities, addresses, booking references and costs.
B9: 3. Set a budget per category on the Budget tab. As you log spending on the Expenses tab, it tracks what's left.
B10: 4. Split costs with friends? Put who paid in the Expenses tab — the Budget tab shows how much each person paid.
B11: 5. Tick things off on the Packing List by choosing ✓ in the Packed column. The progress bar fills up as you go.
B13: Colour key
B14: Pale yellow cells = type here. Everything else calculates automatically — no need to touch it.
B16: Works in Microsoft Excel and Google Sheets (File → Import, or open directly from Google Drive).
B17: The example rows are just there to show you the format — delete or overwrite them.

Sheet Trip Overview
B2: Trip Overview
B3: The big picture. Fill in the yellow cells.
B5: Destination | C5: Lisbon, Portugal
B6: Start date | C6: 46384
B7: End date | C7: 46390
B8: Travellers (comma separated) | C8: Alex, Sam
B9: Total trip budget | C9: 2500
B10: Accommodation | C10: Casa do Rio, Alfama
B11: Accommodation address / phone | C11: Rua de Example 12
B12: Flight out (number & time) | C12: TP1331 · 08:40
B13: Flight back (number & time) | C13: TP1336 · 19:15
B14: Emergency contact
B16: At a glance
B17: Days until you leave | C17: =IF(C6="","",MAX(0,C6-TODAY())) -> 60
B18: Trip length (nights) | C18: =IF(OR(C6="",C7=""),"",C7-C6) -> 6
B19: Budget | C19: =C9 -> 2500
B20: Spent so far | C20: =Budget!D14 -> 1228
B21: Remaining | C21: =C19-C20 -> 1272
B22: Daily spending allowance | C22: =IF(OR(C18="",C18=0),"",C21/C18) -> 212
B23: Packing progress | C23: ='Packing List'!E5 -> 0.21052632

Sheet Itinerary
B2: Itinerary
B3: One row per plan. Day number fills in from the date.
B5: Day | C5: Date | D5: Time | E5: Activity | F5: Location / address | G5: Booking ref | H5: Cost | I5: Notes
B6: =IF(C6="","",C6-'Trip Overview'!$C$6+1) -> 1 | C6: 46384 | D6: 10:00 | E6: Check in & drop bags | F6: Casa do Rio | G6: CR-4471 | H6: 0
B7: =IF(C7="","",C7-'Trip Overview'!$C$6+1) -> 1 | C7: 46384 | D7: 14:00 | E7: Tram 28 ride | F7: Martim Moniz | H7: 6
B8: =IF(C8="","",C8-'Trip Overview'!$C$6+1) -> 2 | C8: 46385 | D8: 09:30 | E8: Belém Tower & pastries | F8: Belém | G8: BT-2219 | H8: 24
B9: =IF(C9="","",C9-'Trip Overview'!$C$6+1) -> 3 | C9: 46386 | D9: All day | E9: Day trip to Sintra | F9: Sintra | H9: 45
B10: =IF(C10="","",C10-'Trip Overview'!$C$6+1)
B11: =IF(C11="","",C11-'Trip Overview'!$C$6+1)
B12: =IF(C12="","",C12-'Trip Overview'!$C$6+1)
B13: =IF(C13="","",C13-'Trip Overview'!$C$6+1)
B14: =IF(C14="","",C14-'Trip Overview'!$C$6+1)
B15: =IF(C15="","",C15-'Trip Overview'!$C$6+1)
B16: =IF(C16="","",C16-'Trip Overview'!$C$6+1)
B17: =IF(C17="","",C17-'Trip Overview'!$C$6+1)
B18: =IF(C18="","",C18-'Trip Overview'!$C$6+1)
B19: =IF(C19="","",C19-'Trip Overview'!$C$6+1)
B20: =IF(C20="","",C20-'Trip Overview'!$C$6+1)
B21: =IF(C21="","",C21-'Trip Overview'!$C$6+1)
... B105: =IF(C105="","",C105-'Trip Overview'!$C$6+1)
G106: Total | H106: =SUM(H6:H105) -> 75

Sheet Budget
B2: Trip Budget
B3: Type a budget per category. Spent comes from the Expenses tab.
B5: Category | C5: Budget | D5: Spent | E5: Left | G5: Traveller | H5: Paid
B6: Flights | C6: 600 | D6: =SUMIFS(Expenses!$E$6:$E$205,Expenses!$D$6:$D$205,B6) -> 420 | E6: =C6-D6 -> 180 | G6: Alex | H6: =IF(G6="","",SUMIFS(Expenses!$E$6:$E$205,Expenses!$F$6:$F$205,G6)) -> 448
B7: Accommodation | C7: 800 | D7: =SUMIFS(Expenses!$E$6:$E$205,Expenses!$D$6:$D$205,B7) -> 780 | E7: =C7-D7 -> 20 | G7: Sam | H7: =IF(G7="","",SUMIFS(Expenses!$E$6:$E$205,Expenses!$F$6:$F$205,G7)) -> 780
B8: Transport | C8: 150 | D8: =SUMIFS(Expenses!$E$6:$E$205,Expenses!$D$6:$D$205,B8) -> 28 | E8: =C8-D8 -> 122 | H8: =IF(G8="","",SUMIFS(Expenses!$E$6:$E$205,Expenses!$F$6:$F$205,G8))
B9: Food & drink | C9: 450 | D9: =SUMIFS(Expenses!$E$6:$E$205,Expenses!$D$6:$D$205,B9) -> 0 | E9: =C9-D9 -> 450 | H9: =IF(G9="","",SUMIFS(Expenses!$E$6:$E$205,Expenses!$F$6:$F$205,G9))
B10: Activities | C10: 300 | D10: =SUMIFS(Expenses!$E$6:$E$205,Expenses!$D$6:$D$205,B10) -> 0 | E10: =C10-D10 -> 300 | H10: =IF(G10="","",SUMIFS(Expenses!$E$6:$E$205,Expenses!$F$6:$F$205,G10))
B11: Shopping | C11: 100 | D11: =SUMIFS(Expenses!$E$6:$E$205,Expenses!$D$6:$D$205,B11) -> 0 | E11: =C11-D11 -> 100
B12: Insurance | C12: 50 | D12: =SUMIFS(Expenses!$E$6:$E$205,Expenses!$D$6:$D$205,B12) -> 0 | E12: =C12-D12 -> 50 | G12: Fair share each | H12: =IF(COUNTA(G6:G10)=0,"",D14/COUNTA(G6:G10)) -> 614
B13: Other | C13: 50 | D13: =SUMIFS(Expenses!$E$6:$E$205,Expenses!$D$6:$D$205,B13) -> 0 | E13: =C13-D13 -> 50 | G13: Paid more than their share? They're owed the difference.
B14: Total | C14: =SUM(C6:C13) -> 2500 | D14: =SUM(D6:D13) -> 1228 | E14: =SUM(E6:E13) -> 1272

Sheet Expenses
B2: Expenses
B3: Log what you actually spend. Category and Paid by feed the Budget tab.
B5: Date | C5: Item | D5: Category | E5: Amount | F5: Paid by
B6: 46324 | C6: Return flights x2 | D6: Flights | E6: 420 | F6: Alex
B7: 46324 | C7: 6 nights apartment | D7: Accommodation | E7: 780 | F7: Sam
B8: 46384 | C8: Airport taxi | D8: Transport | E8: 28 | F8: Alex

Sheet Packing List
B2: Packing List
B3: Choose ✓ when an item is in the bag.
B5: Packed | C5: =COUNTIF(D8:D157,"✓")&" of "&COUNTA(B8:B157)&" items" -> 4 of 19 items | E5: =IF(COUNTA(B8:B157)=0,0,COUNTIF(D8:D157,"✓")/COUNTA(B8:B157)) -> 0.21052632
B7: Item | C7: Category | D7: Packed
B8: Passport | C8: Documents | D8: ✓
B9: Travel insurance docs | C9: Documents | D9: ✓
B10: Boarding passes | C10: Documents | D10: ✓
B11: Bank cards & some cash | C11: Documents | D11: ✓
B12: Phone charger | C12: Tech
B13: Plug adapter | C13: Tech
B14: Headphones | C14: Tech
B15: Power bank | C15: Tech
B16: Toothbrush & toothpaste | C16: Toiletries
B17: Sunscreen | C17: Toiletries
B18: Medication | C18: Toiletries
B19: T-shirts | C19: Clothes
B20: Trousers / shorts | C20: Clothes
B21: Underwear & socks | C21: Clothes
B22: Comfy walking shoes | C22: Clothes
B23: Light jacket | C23: Clothes
... B26: Book / Kindle | C26: Extras
